MANIFEST.in
setup.py
MadeiraCloudAgent/__init__.py
MadeiraCloudAgent/daemon.py
MadeiraCloudAgent.egg-info/PKG-INFO
MadeiraCloudAgent.egg-info/SOURCES.txt
MadeiraCloudAgent.egg-info/dependency_links.txt
MadeiraCloudAgent.egg-info/not-zip-safe
MadeiraCloudAgent.egg-info/top_level.txt
MadeiraCloudAgent/monitor/__init__.py
MadeiraCloudAgent/monitor/agent.py
MadeiraCloudAgent/monitor/collector.py