Metadata-Version: 1.0
Name: MadeiraCloudAgent
Version: 0.1.51
Summary: Agent For MadeiraCloud
Home-page: www.madeiracloud.com
Author: MadeiraCloud
Author-email: support@madeiracloud.com
License: GPL
Keywords: MadeiraCloud,egg
Platform: UNKNOWN
